{
  "generatedAt": "2026-04-05T23:19:28.051Z",
  "title": "WTI Spot and ROC(12)",
  "subtitle": "Monthly WTI spot candles with 12-month rate of change.",
  "source": "FRED DCOILWTICO + Apr-2026 provisional snapshot",
  "currentMonthExtension": {
    "month": "2026-04",
    "date": "2026-04-01",
    "open": 101.72,
    "high": 113.97,
    "low": 96.5,
    "close": 111.54,
    "snapshotDate": "2026-04-02",
    "snapshotSource": "StockCharts reference snapshot provided by user"
  },
  "latest": {
    "month": "2026-04",
    "date": "2026-04-01",
    "open": 101.72,
    "high": 113.97,
    "low": 96.5,
    "close": 111.54,
    "snapshotDate": "2026-04-02",
    "snapshotSource": "StockCharts reference snapshot provided by user",
    "roc12": 87.3
  },
  "range": {
    "start": "1986-01-01",
    "end": "2026-04-01"
  },
  "events": [
    {
      "label": "1987 Crash",
      "date": "1987-10-01"
    },
    {
      "label": "1990 Crash",
      "date": "1990-08-01"
    },
    {
      "label": "DOT COM",
      "date": "2000-03-01"
    },
    {
      "label": "Financial Crisis",
      "date": "2008-10-01"
    },
    {
      "label": "2022 Bear Market\nInflation / War / Rates",
      "date": "2022-06-01"
    },
    {
      "label": "Rally\n2026",
      "date": "2026-01-01",
      "variant": "highlight"
    }
  ],
  "candles": [
    {
      "month": "1986-01",
      "date": "1986-01-01",
      "open": 25.56,
      "high": 26.53,
      "low": 18.95,
      "close": 18.95,
      "roc12": null
    },
    {
      "month": "1986-02",
      "date": "1986-02-01",
      "open": 17.42,
      "high": 17.7,
      "low": 13.23,
      "close": 13.23,
      "roc12": null
    },
    {
      "month": "1986-03",
      "date": "1986-03-01",
      "open": 11.98,
      "high": 14.05,
      "low": 10.25,
      "close": 10.25,
      "roc12": null
    },
    {
      "month": "1986-04",
      "date": "1986-04-01",
      "open": 11.13,
      "high": 14.39,
      "low": 11.13,
      "close": 13.38,
      "roc12": null
    },
    {
      "month": "1986-05",
      "date": "1986-05-01",
      "open": 13.8,
      "high": 17.13,
      "low": 13.8,
      "close": 14.3,
      "roc12": null
    },
    {
      "month": "1986-06",
      "date": "1986-06-01",
      "open": 13.8,
      "high": 14.44,
      "low": 12.38,
      "close": 12.8,
      "roc12": null
    },
    {
      "month": "1986-07",
      "date": "1986-07-01",
      "open": 12.39,
      "high": 13.07,
      "low": 10.83,
      "close": 11.23,
      "roc12": null
    },
    {
      "month": "1986-08",
      "date": "1986-08-01",
      "open": 11.56,
      "high": 15.93,
      "low": 11.56,
      "close": 15.93,
      "roc12": null
    },
    {
      "month": "1986-09",
      "date": "1986-09-01",
      "open": 16.43,
      "high": 16.43,
      "low": 13.8,
      "close": 14.7,
      "roc12": null
    },
    {
      "month": "1986-10",
      "date": "1986-10-01",
      "open": 15.23,
      "high": 15.6,
      "low": 13.73,
      "close": 15.25,
      "roc12": null
    },
    {
      "month": "1986-11",
      "date": "1986-11-01",
      "open": 14.7,
      "high": 15.68,
      "low": 14.7,
      "close": 15,
      "roc12": null
    },
    {
      "month": "1986-12",
      "date": "1986-12-01",
      "open": 15.29,
      "high": 17.93,
      "low": 14.93,
      "close": 17.93,
      "roc12": null
    },
    {
      "month": "1987-01",
      "date": "1987-01-01",
      "open": 18.13,
      "high": 19.13,
      "low": 17.98,
      "close": 18.73,
      "roc12": -1.16
    },
    {
      "month": "1987-02",
      "date": "1987-02-01",
      "open": 18.59,
      "high": 18.59,
      "low": 16.43,
      "close": 16.45,
      "roc12": 24.34
    },
    {
      "month": "1987-03",
      "date": "1987-03-01",
      "open": 16.43,
      "high": 18.94,
      "low": 16.43,
      "close": 18.82,
      "roc12": 83.61
    },
    {
      "month": "1987-04",
      "date": "1987-04-01",
      "open": 18.78,
      "high": 19.03,
      "low": 18.07,
      "close": 18.76,
      "roc12": 40.21
    },
    {
      "month": "1987-05",
      "date": "1987-05-01",
      "open": 18.84,
      "high": 19.97,
      "low": 18.84,
      "close": 19.36,
      "roc12": 35.38
    },
    {
      "month": "1987-06",
      "date": "1987-06-01",
      "open": 19.55,
      "high": 20.65,
      "low": 19.55,
      "close": 20.22,
      "roc12": 57.97
    },
    {
      "month": "1987-07",
      "date": "1987-07-01",
      "open": 20.47,
      "high": 22.44,
      "low": 20.47,
      "close": 21.43,
      "roc12": 90.83
    },
    {
      "month": "1987-08",
      "date": "1987-08-01",
      "open": 22.21,
      "high": 22.21,
      "low": 19.18,
      "close": 19.76,
      "roc12": 24.04
    },
    {
      "month": "1987-09",
      "date": "1987-09-01",
      "open": 19.61,
      "high": 19.77,
      "low": 18.99,
      "close": 19.62,
      "roc12": 33.47
    },
    {
      "month": "1987-10",
      "date": "1987-10-01",
      "open": 19.62,
      "high": 20.23,
      "low": 19.33,
      "close": 19.96,
      "roc12": 30.89
    },
    {
      "month": "1987-11",
      "date": "1987-11-01",
      "open": 19.64,
      "high": 19.64,
      "low": 18.28,
      "close": 18.52,
      "roc12": 23.47
    },
    {
      "month": "1987-12",
      "date": "1987-12-01",
      "open": 18.44,
      "high": 18.87,
      "low": 15.12,
      "close": 16.74,
      "roc12": -6.64
    },
    {
      "month": "1988-01",
      "date": "1988-01-01",
      "open": 17.77,
      "high": 17.89,
      "low": 16.56,
      "close": 16.97,
      "roc12": -9.4
    },
    {
      "month": "1988-02",
      "date": "1988-02-01",
      "open": 16.83,
      "high": 17.7,
      "low": 15.77,
      "close": 15.98,
      "roc12": -2.86
    },
    {
      "month": "1988-03",
      "date": "1988-03-01",
      "open": 15.57,
      "high": 17.09,
      "low": 15.35,
      "close": 17.09,
      "roc12": -9.19
    },
    {
      "month": "1988-04",
      "date": "1988-04-01",
      "open": 16.99,
      "high": 18.54,
      "low": 16.72,
      "close": 18.1,
      "roc12": -3.52
    },
    {
      "month": "1988-05",
      "date": "1988-05-01",
      "open": 17.12,
      "high": 17.72,
      "low": 17.01,
      "close": 17.54,
      "roc12": -9.4
    },
    {
      "month": "1988-06",
      "date": "1988-06-01",
      "open": 17.6,
      "high": 17.67,
      "low": 15.2,
      "close": 15.2,
      "roc12": -24.83
    },
    {
      "month": "1988-07",
      "date": "1988-07-01",
      "open": 14.92,
      "high": 16.37,
      "low": 14.35,
      "close": 16.37,
      "roc12": -23.61
    },
    {
      "month": "1988-08",
      "date": "1988-08-01",
      "open": 16.07,
      "high": 16.07,
      "low": 15.12,
      "close": 15.19,
      "roc12": -23.13
    },
    {
      "month": "1988-09",
      "date": "1988-09-01",
      "open": 15.05,
      "high": 15.38,
      "low": 13.33,
      "close": 13.33,
      "roc12": -32.06
    },
    {
      "month": "1988-10",
      "date": "1988-10-01",
      "open": 13.03,
      "high": 15.33,
      "low": 12.58,
      "close": 13.54,
      "roc12": -32.16
    },
    {
      "month": "1988-11",
      "date": "1988-11-01",
      "open": 13.52,
      "high": 15.43,
      "low": 13.3,
      "close": 15.42,
      "roc12": -16.74
    },
    {
      "month": "1988-12",
      "date": "1988-12-01",
      "open": 15.63,
      "high": 17.68,
      "low": 15.36,
      "close": 17.12,
      "roc12": 2.27
    },
    {
      "month": "1989-01",
      "date": "1989-01-01",
      "open": 17.38,
      "high": 19.28,
      "low": 16.99,
      "close": 17,
      "roc12": 0.18
    },
    {
      "month": "1989-02",
      "date": "1989-02-01",
      "open": 17.5,
      "high": 18.64,
      "low": 17.11,
      "close": 18.21,
      "roc12": 13.95
    },
    {
      "month": "1989-03",
      "date": "1989-03-01",
      "open": 18.3,
      "high": 21.03,
      "low": 18.12,
      "close": 20.27,
      "roc12": 18.61
    },
    {
      "month": "1989-04",
      "date": "1989-04-01",
      "open": 20.03,
      "high": 24.62,
      "low": 19.85,
      "close": 20.38,
      "roc12": 12.6
    },
    {
      "month": "1989-05",
      "date": "1989-05-01",
      "open": 20.66,
      "high": 21.77,
      "low": 19.41,
      "close": 19.93,
      "roc12": 13.63
    },
    {
      "month": "1989-06",
      "date": "1989-06-01",
      "open": 19.83,
      "high": 20.88,
      "low": 19.3,
      "close": 20.29,
      "roc12": 33.49
    },
    {
      "month": "1989-07",
      "date": "1989-07-01",
      "open": 20.55,
      "high": 20.98,
      "low": 17.96,
      "close": 18.33,
      "roc12": 11.97
    },
    {
      "month": "1989-08",
      "date": "1989-08-01",
      "open": 17.91,
      "high": 19.15,
      "low": 17.91,
      "close": 18.83,
      "roc12": 23.96
    },
    {
      "month": "1989-09",
      "date": "1989-09-01",
      "open": 18.88,
      "high": 20.15,
      "low": 18.88,
      "close": 20.15,
      "roc12": 51.16
    },
    {
      "month": "1989-10",
      "date": "1989-10-01",
      "open": 19.99,
      "high": 20.91,
      "low": 19.48,
      "close": 19.88,
      "roc12": 46.82
    },
    {
      "month": "1989-11",
      "date": "1989-11-01",
      "open": 20.09,
      "high": 20.52,
      "low": 19.33,
      "close": 19.87,
      "roc12": 28.86
    },
    {
      "month": "1989-12",
      "date": "1989-12-01",
      "open": 20.26,
      "high": 22.2,
      "low": 20.22,
      "close": 21.84,
      "roc12": 27.57
    },
    {
      "month": "1990-01",
      "date": "1990-01-01",
      "open": 22.88,
      "high": 24.48,
      "low": 21.64,
      "close": 22.69,
      "roc12": 33.47
    },
    {
      "month": "1990-02",
      "date": "1990-02-01",
      "open": 22.71,
      "high": 23.04,
      "low": 21.13,
      "close": 21.55,
      "roc12": 18.34
    },
    {
      "month": "1990-03",
      "date": "1990-03-01",
      "open": 21.19,
      "high": 21.62,
      "low": 19.34,
      "close": 20.34,
      "roc12": 0.35
    },
    {
      "month": "1990-04",
      "date": "1990-04-01",
      "open": 20.51,
      "high": 20.51,
      "low": 16.95,
      "close": 18.5,
      "roc12": -9.22
    },
    {
      "month": "1990-05",
      "date": "1990-05-01",
      "open": 18.76,
      "high": 19.73,
      "low": 16.02,
      "close": 17.47,
      "roc12": -12.34
    },
    {
      "month": "1990-06",
      "date": "1990-06-01",
      "open": 17.51,
      "high": 17.6,
      "low": 15.43,
      "close": 17.05,
      "roc12": -15.97
    },
    {
      "month": "1990-07",
      "date": "1990-07-01",
      "open": 16.94,
      "high": 20.57,
      "low": 16.49,
      "close": 20.57,
      "roc12": 12.22
    },
    {
      "month": "1990-08",
      "date": "1990-08-01",
      "open": 21.59,
      "high": 31.67,
      "low": 21.59,
      "close": 27.45,
      "roc12": 45.78
    },
    {
      "month": "1990-09",
      "date": "1990-09-01",
      "open": 27.45,
      "high": 39.77,
      "low": 27.45,
      "close": 39.53,
      "roc12": 96.18
    },
    {
      "month": "1990-10",
      "date": "1990-10-01",
      "open": 37.08,
      "high": 41.07,
      "low": 28.46,
      "close": 35.31,
      "roc12": 77.62
    },
    {
      "month": "1990-11",
      "date": "1990-11-01",
      "open": 35.3,
      "high": 35.61,
      "low": 29.08,
      "close": 29.08,
      "roc12": 46.35
    },
    {
      "month": "1990-12",
      "date": "1990-12-01",
      "open": 29.4,
      "high": 29.4,
      "low": 25.3,
      "close": 28.48,
      "roc12": 30.4
    },
    {
      "month": "1991-01",
      "date": "1991-01-01",
      "open": 26.53,
      "high": 32.25,
      "low": 20.05,
      "close": 21.9,
      "roc12": -3.48
    },
    {
      "month": "1991-02",
      "date": "1991-02-01",
      "open": 21.33,
      "high": 22.78,
      "low": 17.43,
      "close": 19.28,
      "roc12": -10.53
    },
    {
      "month": "1991-03",
      "date": "1991-03-01",
      "open": 19.43,
      "high": 20.78,
      "low": 19,
      "close": 19.63,
      "roc12": -3.49
    },
    {
      "month": "1991-04",
      "date": "1991-04-01",
      "open": 19.28,
      "high": 21.85,
      "low": 19.28,
      "close": 20.99,
      "roc12": 13.46
    },
    {
      "month": "1991-05",
      "date": "1991-05-01",
      "open": 21.28,
      "high": 21.92,
      "low": 20.73,
      "close": 21.16,
      "roc12": 21.12
    },
    {
      "month": "1991-06",
      "date": "1991-06-01",
      "open": 21.16,
      "high": 21.16,
      "low": 19.7,
      "close": 20.56,
      "roc12": 20.59
    },
    {
      "month": "1991-07",
      "date": "1991-07-01",
      "open": 20.78,
      "high": 22.2,
      "low": 20.69,
      "close": 21.7,
      "roc12": 5.49
    },
    {
      "month": "1991-08",
      "date": "1991-08-01",
      "open": 21.33,
      "high": 22.5,
      "low": 21.29,
      "close": 22.28,
      "roc12": -18.83
    },
    {
      "month": "1991-09",
      "date": "1991-09-01",
      "open": 22.28,
      "high": 22.42,
      "low": 21.36,
      "close": 22.25,
      "roc12": -43.71
    },
    {
      "month": "1991-10",
      "date": "1991-10-01",
      "open": 22.1,
      "high": 24.12,
      "low": 22.1,
      "close": 23.29,
      "roc12": -34.04
    },
    {
      "month": "1991-11",
      "date": "1991-11-01",
      "open": 23.85,
      "high": 23.85,
      "low": 21.04,
      "close": 21.48,
      "roc12": -26.13
    },
    {
      "month": "1991-12",
      "date": "1991-12-01",
      "open": 21.1,
      "high": 21.1,
      "low": 18.28,
      "close": 19.15,
      "roc12": -32.76
    },
    {
      "month": "1992-01",
      "date": "1992-01-01",
      "open": 19.43,
      "high": 19.43,
      "low": 17.89,
      "close": 18.93,
      "roc12": -13.56
    },
    {
      "month": "1992-02",
      "date": "1992-02-01",
      "open": 18.97,
      "high": 19.91,
      "low": 18.14,
      "close": 18.69,
      "roc12": -3.06
    },
    {
      "month": "1992-03",
      "date": "1992-03-01",
      "open": 18.36,
      "high": 19.49,
      "low": 18.36,
      "close": 19.49,
      "roc12": -0.71
    },
    {
      "month": "1992-04",
      "date": "1992-04-01",
      "open": 19.85,
      "high": 20.88,
      "low": 19.79,
      "close": 20.88,
      "roc12": -0.52
    },
    {
      "month": "1992-05",
      "date": "1992-05-01",
      "open": 20.88,
      "high": 22.13,
      "low": 20.12,
      "close": 22.13,
      "roc12": 4.58
    },
    {
      "month": "1992-06",
      "date": "1992-06-01",
      "open": 22.07,
      "high": 23.03,
      "low": 21.84,
      "close": 21.84,
      "roc12": 6.23
    },
    {
      "month": "1992-07",
      "date": "1992-07-01",
      "open": 21.9,
      "high": 22.11,
      "low": 21.25,
      "close": 21.83,
      "roc12": 0.6
    },
    {
      "month": "1992-08",
      "date": "1992-08-01",
      "open": 21.6,
      "high": 21.85,
      "low": 21,
      "close": 21.46,
      "roc12": -3.68
    },
    {
      "month": "1992-09",
      "date": "1992-09-01",
      "open": 21.72,
      "high": 22.39,
      "low": 21.51,
      "close": 21.83,
      "roc12": -1.89
    },
    {
      "month": "1992-10",
      "date": "1992-10-01",
      "open": 21.83,
      "high": 22.37,
      "low": 20.68,
      "close": 20.68,
      "roc12": -11.21
    },
    {
      "month": "1992-11",
      "date": "1992-11-01",
      "open": 20.77,
      "high": 20.77,
      "low": 19.91,
      "close": 19.91,
      "roc12": -7.31
    },
    {
      "month": "1992-12",
      "date": "1992-12-01",
      "open": 19.56,
      "high": 19.97,
      "low": 18.69,
      "close": 19.49,
      "roc12": 1.78
    },
    {
      "month": "1993-01",
      "date": "1993-01-01",
      "open": 19.03,
      "high": 20.38,
      "low": 18.21,
      "close": 20.27,
      "roc12": 7.08
    },
    {
      "month": "1993-02",
      "date": "1993-02-01",
      "open": 20.32,
      "high": 20.63,
      "low": 19.3,
      "close": 20.53,
      "roc12": 9.84
    },
    {
      "month": "1993-03",
      "date": "1993-03-01",
      "open": 20.62,
      "high": 21.05,
      "low": 19.52,
      "close": 20.44,
      "roc12": 4.87
    },
    {
      "month": "1993-04",
      "date": "1993-04-01",
      "open": 20.54,
      "high": 20.67,
      "low": 19.79,
      "close": 20.54,
      "roc12": -1.63
    },
    {
      "month": "1993-05",
      "date": "1993-05-01",
      "open": 20.58,
      "high": 20.58,
      "low": 19.15,
      "close": 20.04,
      "roc12": -9.44
    },
    {
      "month": "1993-06",
      "date": "1993-06-01",
      "open": 20.2,
      "high": 20.2,
      "low": 18.35,
      "close": 18.82,
      "roc12": -13.83
    },
    {
      "month": "1993-07",
      "date": "1993-07-01",
      "open": 18.44,
      "high": 18.5,
      "low": 17.2,
      "close": 17.94,
      "roc12": -17.82
    },
    {
      "month": "1993-08",
      "date": "1993-08-01",
      "open": 17.9,
      "high": 18.82,
      "low": 17.3,
      "close": 18.24,
      "roc12": -15
    },
    {
      "month": "1993-09",
      "date": "1993-09-01",
      "open": 17.92,
      "high": 18.73,
      "low": 16.74,
      "close": 18.72,
      "roc12": -14.25
    },
    {
      "month": "1993-10",
      "date": "1993-10-01",
      "open": 18.63,
      "high": 18.76,
      "low": 16.97,
      "close": 16.97,
      "roc12": -17.94
    },
    {
      "month": "1993-11",
      "date": "1993-11-01",
      "open": 17.5,
      "high": 17.5,
      "low": 15.3,
      "close": 15.36,
      "roc12": -22.85
    },
    {
      "month": "1993-12",
      "date": "1993-12-01",
      "open": 15.45,
      "high": 15.45,
      "low": 13.98,
      "close": 14.19,
      "roc12": -27.19
    },
    {
      "month": "1994-01",
      "date": "1994-01-01",
      "open": 14.52,
      "high": 15.5,
      "low": 14.36,
      "close": 15.24,
      "roc12": -24.81
    },
    {
      "month": "1994-02",
      "date": "1994-02-01",
      "open": 15.91,
      "high": 16.06,
      "low": 13.89,
      "close": 14.5,
      "roc12": -29.37
    },
    {
      "month": "1994-03",
      "date": "1994-03-01",
      "open": 14.78,
      "high": 15.37,
      "low": 14.14,
      "close": 14.78,
      "roc12": -27.69
    },
    {
      "month": "1994-04",
      "date": "1994-04-01",
      "open": 15.67,
      "high": 17.84,
      "low": 15.57,
      "close": 16.92,
      "roc12": -17.62
    },
    {
      "month": "1994-05",
      "date": "1994-05-01",
      "open": 17.18,
      "high": 18.93,
      "low": 16.85,
      "close": 18.3,
      "roc12": -8.68
    },
    {
      "month": "1994-06",
      "date": "1994-06-01",
      "open": 18.29,
      "high": 20.72,
      "low": 17.78,
      "close": 19.37,
      "roc12": 2.92
    },
    {
      "month": "1994-07",
      "date": "1994-07-01",
      "open": 19.52,
      "high": 20.4,
      "low": 19.15,
      "close": 20.3,
      "roc12": 13.15
    },
    {
      "month": "1994-08",
      "date": "1994-08-01",
      "open": 20.65,
      "high": 20.65,
      "low": 16.87,
      "close": 17.6,
      "roc12": -3.51
    },
    {
      "month": "1994-09",
      "date": "1994-09-01",
      "open": 17.47,
      "high": 18.36,
      "low": 16.72,
      "close": 18.36,
      "roc12": -1.92
    },
    {
      "month": "1994-10",
      "date": "1994-10-01",
      "open": 18.16,
      "high": 18.27,
      "low": 16.98,
      "close": 18.16,
      "roc12": 7.01
    },
    {
      "month": "1994-11",
      "date": "1994-11-01",
      "open": 18.66,
      "high": 18.97,
      "low": 17.38,
      "close": 18.06,
      "roc12": 17.58
    },
    {
      "month": "1994-12",
      "date": "1994-12-01",
      "open": 17.77,
      "high": 17.77,
      "low": 16.6,
      "close": 17.77,
      "roc12": 25.23
    },
    {
      "month": "1995-01",
      "date": "1995-01-01",
      "open": 17.45,
      "high": 18.82,
      "low": 17.4,
      "close": 18.48,
      "roc12": 21.26
    },
    {
      "month": "1995-02",
      "date": "1995-02-01",
      "open": 18.48,
      "high": 18.94,
      "low": 18.28,
      "close": 18.52,
      "roc12": 27.72
    },
    {
      "month": "1995-03",
      "date": "1995-03-01",
      "open": 18.31,
      "high": 19.21,
      "low": 17.9,
      "close": 19.18,
      "roc12": 29.77
    },
    {
      "month": "1995-04",
      "date": "1995-04-01",
      "open": 19.05,
      "high": 20.52,
      "low": 19.05,
      "close": 20.36,
      "roc12": 20.33
    },
    {
      "month": "1995-05",
      "date": "1995-05-01",
      "open": 20.53,
      "high": 20.53,
      "low": 18.7,
      "close": 18.88,
      "roc12": 3.17
    },
    {
      "month": "1995-06",
      "date": "1995-06-01",
      "open": 18.89,
      "high": 19.25,
      "low": 17.38,
      "close": 17.38,
      "roc12": -10.27
    },
    {
      "month": "1995-07",
      "date": "1995-07-01",
      "open": 17.33,
      "high": 17.62,
      "low": 17.03,
      "close": 17.62,
      "roc12": -13.2
    },
    {
      "month": "1995-08",
      "date": "1995-08-01",
      "open": 17.59,
      "high": 19.91,
      "low": 17.4,
      "close": 17.89,
      "roc12": 1.65
    },
    {
      "month": "1995-09",
      "date": "1995-09-01",
      "open": 18.08,
      "high": 19.01,
      "low": 17.27,
      "close": 17.54,
      "roc12": -4.47
    },
    {
      "month": "1995-10",
      "date": "1995-10-01",
      "open": 17.67,
      "high": 17.67,
      "low": 16.86,
      "close": 17.67,
      "roc12": -2.7
    },
    {
      "month": "1995-11",
      "date": "1995-11-01",
      "open": 17.74,
      "high": 18.56,
      "low": 17.62,
      "close": 18.27,
      "roc12": 1.16
    },
    {
      "month": "1995-12",
      "date": "1995-12-01",
      "open": 18.43,
      "high": 19.71,
      "low": 18.43,
      "close": 19.54,
      "roc12": 9.96
    },
    {
      "month": "1996-01",
      "date": "1996-01-01",
      "open": 19.83,
      "high": 20.5,
      "low": 17.33,
      "close": 17.76,
      "roc12": -3.9
    },
    {
      "month": "1996-02",
      "date": "1996-02-01",
      "open": 17.63,
      "high": 22.14,
      "low": 17.53,
      "close": 19.59,
      "roc12": 5.78
    },
    {
      "month": "1996-03",
      "date": "1996-03-01",
      "open": 19.45,
      "high": 24.56,
      "low": 19.24,
      "close": 21.43,
      "roc12": 11.73
    },
    {
      "month": "1996-04",
      "date": "1996-04-01",
      "open": 22.29,
      "high": 25.15,
      "low": 20.95,
      "close": 20.95,
      "roc12": 2.9
    },
    {
      "month": "1996-05",
      "date": "1996-05-01",
      "open": 20.81,
      "high": 23.02,
      "low": 19.77,
      "close": 19.77,
      "roc12": 4.71
    },
    {
      "month": "1996-06",
      "date": "1996-06-01",
      "open": 19.86,
      "high": 21.53,
      "low": 19.73,
      "close": 20.92,
      "roc12": 20.37
    },
    {
      "month": "1996-07",
      "date": "1996-07-01",
      "open": 21.48,
      "high": 22.43,
      "low": 20.13,
      "close": 20.46,
      "roc12": 16.12
    },
    {
      "month": "1996-08",
      "date": "1996-08-01",
      "open": 20.95,
      "high": 23.1,
      "low": 20.95,
      "close": 22.25,
      "roc12": 24.37
    },
    {
      "month": "1996-09",
      "date": "1996-09-01",
      "open": 23.35,
      "high": 24.95,
      "low": 23.25,
      "close": 24.2,
      "roc12": 37.97
    },
    {
      "month": "1996-10",
      "date": "1996-10-01",
      "open": 24.35,
      "high": 25.85,
      "low": 23.25,
      "close": 23.25,
      "roc12": 31.58
    },
    {
      "month": "1996-11",
      "date": "1996-11-01",
      "open": 23,
      "high": 25.75,
      "low": 22.65,
      "close": 23.7,
      "roc12": 29.72
    },
    {
      "month": "1996-12",
      "date": "1996-12-01",
      "open": 24.7,
      "high": 26.55,
      "low": 23.4,
      "close": 25.9,
      "roc12": 32.55
    },
    {
      "month": "1997-01",
      "date": "1997-01-01",
      "open": 25.55,
      "high": 26.55,
      "low": 23.85,
      "close": 24.15,
      "roc12": 35.98
    },
    {
      "month": "1997-02",
      "date": "1997-02-01",
      "open": 24.2,
      "high": 24.2,
      "low": 20.3,
      "close": 20.3,
      "roc12": 3.62
    },
    {
      "month": "1997-03",
      "date": "1997-03-01",
      "open": 20.25,
      "high": 22,
      "low": 20.15,
      "close": 20.35,
      "roc12": -5.04
    },
    {
      "month": "1997-04",
      "date": "1997-04-01",
      "open": 20.3,
      "high": 20.4,
      "low": 19.15,
      "close": 20.2,
      "roc12": -3.58
    },
    {
      "month": "1997-05",
      "date": "1997-05-01",
      "open": 19.9,
      "high": 22.1,
      "low": 19.6,
      "close": 21,
      "roc12": 6.22
    },
    {
      "month": "1997-06",
      "date": "1997-06-01",
      "open": 21.15,
      "high": 21.15,
      "low": 18.6,
      "close": 19.82,
      "roc12": -5.26
    },
    {
      "month": "1997-07",
      "date": "1997-07-01",
      "open": 20.11,
      "high": 20.43,
      "low": 18.92,
      "close": 20.19,
      "roc12": -1.32
    },
    {
      "month": "1997-08",
      "date": "1997-08-01",
      "open": 20.27,
      "high": 20.81,
      "low": 19.29,
      "close": 19.66,
      "roc12": -11.64
    },
    {
      "month": "1997-09",
      "date": "1997-09-01",
      "open": 19.73,
      "high": 21.29,
      "low": 19.3,
      "close": 21.13,
      "roc12": -12.69
    },
    {
      "month": "1997-10",
      "date": "1997-10-01",
      "open": 21.02,
      "high": 22.86,
      "low": 20.4,
      "close": 21.1,
      "roc12": -9.25
    },
    {
      "month": "1997-11",
      "date": "1997-11-01",
      "open": 20.91,
      "high": 21.01,
      "low": 19.13,
      "close": 19.13,
      "roc12": -19.28
    },
    {
      "month": "1997-12",
      "date": "1997-12-01",
      "open": 18.76,
      "high": 18.86,
      "low": 17.6,
      "close": 17.65,
      "roc12": -31.85
    },
    {
      "month": "1998-01",
      "date": "1998-01-01",
      "open": 17.41,
      "high": 17.93,
      "low": 15.65,
      "close": 17.21,
      "roc12": -28.74
    },
    {
      "month": "1998-02",
      "date": "1998-02-01",
      "open": 17.07,
      "high": 17.07,
      "low": 15.14,
      "close": 15.44,
      "roc12": -23.94
    },
    {
      "month": "1998-03",
      "date": "1998-03-01",
      "open": 15.32,
      "high": 16.92,
      "low": 13.41,
      "close": 15.75,
      "roc12": -22.6
    },
    {
      "month": "1998-04",
      "date": "1998-04-01",
      "open": 15.69,
      "high": 16.08,
      "low": 13.09,
      "close": 15.56,
      "roc12": -22.97
    },
    {
      "month": "1998-05",
      "date": "1998-05-01",
      "open": 16.25,
      "high": 16.25,
      "low": 13.01,
      "close": 15.21,
      "roc12": -27.57
    },
    {
      "month": "1998-06",
      "date": "1998-06-01",
      "open": 14.99,
      "high": 15.24,
      "low": 11.69,
      "close": 14.3,
      "roc12": -27.85
    },
    {
      "month": "1998-07",
      "date": "1998-07-01",
      "open": 14.47,
      "high": 14.9,
      "low": 13.44,
      "close": 14.27,
      "roc12": -29.32
    },
    {
      "month": "1998-08",
      "date": "1998-08-01",
      "open": 13.93,
      "high": 13.93,
      "low": 12.76,
      "close": 13.29,
      "roc12": -32.4
    },
    {
      "month": "1998-09",
      "date": "1998-09-01",
      "open": 13.62,
      "high": 16.19,
      "low": 13.62,
      "close": 16.19,
      "roc12": -23.38
    },
    {
      "month": "1998-10",
      "date": "1998-10-01",
      "open": 15.52,
      "high": 15.71,
      "low": 13.39,
      "close": 14.48,
      "roc12": -31.37
    },
    {
      "month": "1998-11",
      "date": "1998-11-01",
      "open": 14.45,
      "high": 14.45,
      "low": 10.86,
      "close": 11.37,
      "roc12": -40.56
    },
    {
      "month": "1998-12",
      "date": "1998-12-01",
      "open": 11.27,
      "high": 12.55,
      "low": 10.82,
      "close": 12.14,
      "roc12": -31.22
    },
    {
      "month": "1999-01",
      "date": "1999-01-01",
      "open": 12.42,
      "high": 13.43,
      "low": 11.82,
      "close": 12.81,
      "roc12": -25.57
    },
    {
      "month": "1999-02",
      "date": "1999-02-01",
      "open": 12.36,
      "high": 12.61,
      "low": 11.38,
      "close": 12.31,
      "roc12": -20.27
    },
    {
      "month": "1999-03",
      "date": "1999-03-01",
      "open": 12.28,
      "high": 16.66,
      "low": 12.28,
      "close": 16.66,
      "roc12": 5.78
    },
    {
      "month": "1999-04",
      "date": "1999-04-01",
      "open": 16.65,
      "high": 18.69,
      "low": 15.92,
      "close": 18.69,
      "roc12": 20.12
    },
    {
      "month": "1999-05",
      "date": "1999-05-01",
      "open": 18.83,
      "high": 18.94,
      "low": 16.77,
      "close": 16.85,
      "roc12": 10.78
    },
    {
      "month": "1999-06",
      "date": "1999-06-01",
      "open": 16.31,
      "high": 19.33,
      "low": 16.31,
      "close": 19.33,
      "roc12": 35.17
    },
    {
      "month": "1999-07",
      "date": "1999-07-01",
      "open": 19.39,
      "high": 21.09,
      "low": 19.38,
      "close": 20.52,
      "roc12": 43.8
    },
    {
      "month": "1999-08",
      "date": "1999-08-01",
      "open": 20.46,
      "high": 22.15,
      "low": 20.21,
      "close": 22.15,
      "roc12": 66.67
    },
    {
      "month": "1999-09",
      "date": "1999-09-01",
      "open": 21.79,
      "high": 24.81,
      "low": 21.54,
      "close": 24.54,
      "roc12": 51.58
    },
    {
      "month": "1999-10",
      "date": "1999-10-01",
      "open": 24.51,
      "high": 24.51,
      "low": 20.81,
      "close": 21.79,
      "roc12": 50.48
    },
    {
      "month": "1999-11",
      "date": "1999-11-01",
      "open": 22.44,
      "high": 28.03,
      "low": 22.44,
      "close": 24.87,
      "roc12": 118.73
    },
    {
      "month": "1999-12",
      "date": "1999-12-01",
      "open": 25.01,
      "high": 26.81,
      "low": 25.01,
      "close": 25.76,
      "roc12": 112.19
    },
    {
      "month": "2000-01",
      "date": "2000-01-01",
      "open": 25.56,
      "high": 30.28,
      "low": 24.65,
      "close": 27.65,
      "roc12": 115.85
    },
    {
      "month": "2000-02",
      "date": "2000-02-01",
      "open": 28.28,
      "high": 30.57,
      "low": 27.52,
      "close": 30.57,
      "roc12": 148.33
    },
    {
      "month": "2000-03",
      "date": "2000-03-01",
      "open": 31.71,
      "high": 33.9,
      "low": 26.36,
      "close": 26.86,
      "roc12": 61.22
    },
    {
      "month": "2000-04",
      "date": "2000-04-01",
      "open": 26.28,
      "high": 27.41,
      "low": 23.91,
      "close": 25.71,
      "roc12": 37.56
    },
    {
      "month": "2000-05",
      "date": "2000-05-01",
      "open": 25.84,
      "high": 30.43,
      "low": 25.84,
      "close": 29.03,
      "roc12": 72.28
    },
    {
      "month": "2000-06",
      "date": "2000-06-01",
      "open": 30.19,
      "high": 34.76,
      "low": 29.29,
      "close": 32.44,
      "roc12": 67.82
    },
    {
      "month": "2000-07",
      "date": "2000-07-01",
      "open": 30.76,
      "high": 31.94,
      "low": 27.5,
      "close": 27.5,
      "roc12": 34.02
    },
    {
      "month": "2000-08",
      "date": "2000-08-01",
      "open": 27.85,
      "high": 34.01,
      "low": 27.85,
      "close": 33.09,
      "roc12": 49.39
    },
    {
      "month": "2000-09",
      "date": "2000-09-01",
      "open": 33.42,
      "high": 37.22,
      "low": 30.26,
      "close": 30.87,
      "roc12": 25.79
    },
    {
      "month": "2000-10",
      "date": "2000-10-01",
      "open": 32.05,
      "high": 36.06,
      "low": 30.66,
      "close": 32.7,
      "roc12": 50.07
    },
    {
      "month": "2000-11",
      "date": "2000-11-01",
      "open": 33.14,
      "high": 36.24,
      "low": 32.59,
      "close": 33.61,
      "roc12": 35.14
    },
    {
      "month": "2000-12",
      "date": "2000-12-01",
      "open": 32.06,
      "high": 32.06,
      "low": 25.82,
      "close": 26.72,
      "roc12": 3.73
    },
    {
      "month": "2001-01",
      "date": "2001-01-01",
      "open": 27.29,
      "high": 32.21,
      "low": 27.29,
      "close": 28.62,
      "roc12": 3.51
    },
    {
      "month": "2001-02",
      "date": "2001-02-01",
      "open": 29.88,
      "high": 31.57,
      "low": 27.35,
      "close": 27.35,
      "roc12": -10.53
    },
    {
      "month": "2001-03",
      "date": "2001-03-01",
      "open": 27.78,
      "high": 28.95,
      "low": 25.99,
      "close": 26.37,
      "roc12": -1.82
    },
    {
      "month": "2001-04",
      "date": "2001-04-01",
      "open": 25.7,
      "high": 28.81,
      "low": 25.24,
      "close": 28.48,
      "roc12": 10.77
    },
    {
      "month": "2001-05",
      "date": "2001-05-01",
      "open": 28.37,
      "high": 29.96,
      "low": 27.35,
      "close": 28.39,
      "roc12": -2.2
    },
    {
      "month": "2001-06",
      "date": "2001-06-01",
      "open": 27.88,
      "high": 29.13,
      "low": 25.67,
      "close": 26.37,
      "roc12": -18.71
    },
    {
      "month": "2001-07",
      "date": "2001-07-01",
      "open": 26.02,
      "high": 28.1,
      "low": 24.65,
      "close": 26.7,
      "roc12": -2.91
    },
    {
      "month": "2001-08",
      "date": "2001-08-01",
      "open": 26.83,
      "high": 28.34,
      "low": 25.63,
      "close": 26.65,
      "roc12": -19.46
    },
    {
      "month": "2001-09",
      "date": "2001-09-01",
      "open": 26.94,
      "high": 29.59,
      "low": 21.46,
      "close": 23.44,
      "roc12": -24.07
    },
    {
      "month": "2001-10",
      "date": "2001-10-01",
      "open": 23.12,
      "high": 23.49,
      "low": 21.2,
      "close": 21.2,
      "roc12": -35.17
    },
    {
      "month": "2001-11",
      "date": "2001-11-01",
      "open": 20.47,
      "high": 22.23,
      "low": 17.5,
      "close": 19.46,
      "roc12": -42.1
    },
    {
      "month": "2001-12",
      "date": "2001-12-01",
      "open": 20.27,
      "high": 21.32,
      "low": 18.04,
      "close": 19.96,
      "roc12": -25.3
    },
    {
      "month": "2002-01",
      "date": "2002-01-01",
      "open": 21.13,
      "high": 21.47,
      "low": 18.02,
      "close": 19.71,
      "roc12": -31.13
    },
    {
      "month": "2002-02",
      "date": "2002-02-01",
      "open": 20.4,
      "high": 21.78,
      "low": 19.75,
      "close": 21.78,
      "roc12": -20.37
    },
    {
      "month": "2002-03",
      "date": "2002-03-01",
      "open": 22.37,
      "high": 26.21,
      "low": 22.37,
      "close": 26.21,
      "roc12": -0.61
    },
    {
      "month": "2002-04",
      "date": "2002-04-01",
      "open": 26.82,
      "high": 27.75,
      "low": 23.51,
      "close": 27.32,
      "roc12": -4.07
    },
    {
      "month": "2002-05",
      "date": "2002-05-01",
      "open": 26.58,
      "high": 29.17,
      "low": 24.78,
      "close": 25.37,
      "roc12": -10.64
    },
    {
      "month": "2002-06",
      "date": "2002-06-01",
      "open": 25.1,
      "high": 26.79,
      "low": 24.21,
      "close": 26.79,
      "roc12": 1.59
    },
    {
      "month": "2002-07",
      "date": "2002-07-01",
      "open": 26.79,
      "high": 27.88,
      "low": 26.14,
      "close": 27.02,
      "roc12": 1.2
    },
    {
      "month": "2002-08",
      "date": "2002-08-01",
      "open": 26.51,
      "high": 30.37,
      "low": 26.51,
      "close": 28.97,
      "roc12": 8.71
    },
    {
      "month": "2002-09",
      "date": "2002-09-01",
      "open": 27.76,
      "high": 30.85,
      "low": 27.76,
      "close": 30.59,
      "roc12": 30.5
    },
    {
      "month": "2002-10",
      "date": "2002-10-01",
      "open": 30.71,
      "high": 30.71,
      "low": 26.81,
      "close": 27.18,
      "roc12": 28.21
    },
    {
      "month": "2002-11",
      "date": "2002-11-01",
      "open": 27.04,
      "high": 27.73,
      "low": 25.28,
      "close": 26.87,
      "roc12": 38.08
    },
    {
      "month": "2002-12",
      "date": "2002-12-01",
      "open": 27.27,
      "high": 32.68,
      "low": 26.8,
      "close": 31.21,
      "roc12": 56.36
    },
    {
      "month": "2003-01",
      "date": "2003-01-01",
      "open": 31.97,
      "high": 34.98,
      "low": 30.66,
      "close": 33.51,
      "roc12": 70.02
    },
    {
      "month": "2003-02",
      "date": "2003-02-01",
      "open": 32.84,
      "high": 37.96,
      "low": 32.84,
      "close": 36.76,
      "roc12": 68.78
    },
    {
      "month": "2003-03",
      "date": "2003-03-01",
      "open": 36.1,
      "high": 37.87,
      "low": 27.18,
      "close": 31.14,
      "roc12": 18.81
    },
    {
      "month": "2003-04",
      "date": "2003-04-01",
      "open": 29.48,
      "high": 30.76,
      "low": 25.25,
      "close": 26.09,
      "roc12": -4.5
    },
    {
      "month": "2003-05",
      "date": "2003-05-01",
      "open": 26.05,
      "high": 29.74,
      "low": 25.65,
      "close": 29.56,
      "roc12": 16.52
    },
    {
      "month": "2003-06",
      "date": "2003-06-01",
      "open": 30.72,
      "high": 32.17,
      "low": 28.97,
      "close": 30.15,
      "roc12": 12.54
    },
    {
      "month": "2003-07",
      "date": "2003-07-01",
      "open": 30.41,
      "high": 31.96,
      "low": 29.98,
      "close": 30.56,
      "roc12": 13.1
    },
    {
      "month": "2003-08",
      "date": "2003-08-01",
      "open": 32.23,
      "high": 32.41,
      "low": 30.76,
      "close": 31.76,
      "roc12": 9.63
    },
    {
      "month": "2003-09",
      "date": "2003-09-01",
      "open": 29.57,
      "high": 29.57,
      "low": 26.93,
      "close": 29.19,
      "roc12": -4.58
    },
    {
      "month": "2003-10",
      "date": "2003-10-01",
      "open": 29.43,
      "high": 32.01,
      "low": 28.67,
      "close": 29.24,
      "roc12": 7.58
    },
    {
      "month": "2003-11",
      "date": "2003-11-01",
      "open": 28.81,
      "high": 33.16,
      "low": 28.81,
      "close": 30.33,
      "roc12": 12.88
    },
    {
      "month": "2003-12",
      "date": "2003-12-01",
      "open": 29.89,
      "high": 33.72,
      "low": 29.89,
      "close": 32.51,
      "roc12": 4.17
    },
    {
      "month": "2004-01",
      "date": "2004-01-01",
      "open": 33.71,
      "high": 36.21,
      "low": 32.86,
      "close": 33.16,
      "roc12": -1.04
    },
    {
      "month": "2004-02",
      "date": "2004-02-01",
      "open": 34.02,
      "high": 37.28,
      "low": 32.49,
      "close": 36.08,
      "roc12": -1.85
    },
    {
      "month": "2004-03",
      "date": "2004-03-01",
      "open": 36.85,
      "high": 38.21,
      "low": 35.41,
      "close": 35.75,
      "roc12": 14.8
    },
    {
      "month": "2004-04",
      "date": "2004-04-01",
      "open": 34.47,
      "high": 37.79,
      "low": 34.29,
      "close": 37.31,
      "roc12": 43
    },
    {
      "month": "2004-05",
      "date": "2004-05-01",
      "open": 38.26,
      "high": 42.03,
      "low": 38.26,
      "close": 39.9,
      "roc12": 34.98
    },
    {
      "month": "2004-06",
      "date": "2004-06-01",
      "open": 42.33,
      "high": 42.33,
      "low": 35.6,
      "close": 36.92,
      "roc12": 22.45
    },
    {
      "month": "2004-07",
      "date": "2004-07-01",
      "open": 38.56,
      "high": 43.72,
      "low": 38.37,
      "close": 43.72,
      "roc12": 43.06
    },
    {
      "month": "2004-08",
      "date": "2004-08-01",
      "open": 43.83,
      "high": 48.66,
      "low": 42.23,
      "close": 42.23,
      "roc12": 32.97
    },
    {
      "month": "2004-09",
      "date": "2004-09-01",
      "open": 43.89,
      "high": 49.76,
      "low": 42.77,
      "close": 49.56,
      "roc12": 69.78
    },
    {
      "month": "2004-10",
      "date": "2004-10-01",
      "open": 50.16,
      "high": 56.37,
      "low": 49.85,
      "close": 51.78,
      "roc12": 77.09
    },
    {
      "month": "2004-11",
      "date": "2004-11-01",
      "open": 50.1,
      "high": 50.9,
      "low": 46.1,
      "close": 49.16,
      "roc12": 62.08
    },
    {
      "month": "2004-12",
      "date": "2004-12-01",
      "open": 45.56,
      "high": 46.31,
      "low": 40.71,
      "close": 43.36,
      "roc12": 33.37
    },
    {
      "month": "2005-01",
      "date": "2005-01-01",
      "open": 42.16,
      "high": 49.43,
      "low": 42.16,
      "close": 48.25,
      "roc12": 45.51
    },
    {
      "month": "2005-02",
      "date": "2005-02-01",
      "open": 47.1,
      "high": 52.2,
      "low": 45.35,
      "close": 51.75,
      "roc12": 43.43
    },
    {
      "month": "2005-03",
      "date": "2005-03-01",
      "open": 51.67,
      "high": 56.8,
      "low": 49.43,
      "close": 55.31,
      "roc12": 54.71
    },
    {
      "month": "2005-04",
      "date": "2005-04-01",
      "open": 57.26,
      "high": 57.26,
      "low": 49.2,
      "close": 49.2,
      "roc12": 31.87
    },
    {
      "month": "2005-05",
      "date": "2005-05-01",
      "open": 50.94,
      "high": 52.08,
      "low": 46.99,
      "close": 52.08,
      "roc12": 30.53
    },
    {
      "month": "2005-06",
      "date": "2005-06-01",
      "open": 54.4,
      "high": 59.78,
      "low": 52.51,
      "close": 56.63,
      "roc12": 53.39
    },
    {
      "month": "2005-07",
      "date": "2005-07-01",
      "open": 59.11,
      "high": 61.24,
      "low": 56.73,
      "close": 60.71,
      "roc12": 38.86
    },
    {
      "month": "2005-08",
      "date": "2005-08-01",
      "open": 61.51,
      "high": 69.91,
      "low": 60.76,
      "close": 68.63,
      "roc12": 62.51
    },
    {
      "month": "2005-09",
      "date": "2005-09-01",
      "open": 69.5,
      "high": 69.5,
      "low": 62.91,
      "close": 66.21,
      "roc12": 33.6
    },
    {
      "month": "2005-10",
      "date": "2005-10-01",
      "open": 65.36,
      "high": 65.36,
      "low": 59.8,
      "close": 59.8,
      "roc12": 15.49
    },
    {
      "month": "2005-11",
      "date": "2005-11-01",
      "open": 59.85,
      "high": 61.7,
      "low": 56.2,
      "close": 57.33,
      "roc12": 16.62
    },
    {
      "month": "2005-12",
      "date": "2005-12-01",
      "open": 58.46,
      "high": 61.36,
      "low": 57.31,
      "close": 61.06,
      "roc12": 40.82
    },
    {
      "month": "2006-01",
      "date": "2006-01-01",
      "open": 63.11,
      "high": 68.36,
      "low": 62.81,
      "close": 67.86,
      "roc12": 40.64
    },
    {
      "month": "2006-02",
      "date": "2006-02-01",
      "open": 66.61,
      "high": 66.61,
      "low": 57.61,
      "close": 61.37,
      "roc12": 18.59
    },
    {
      "month": "2006-03",
      "date": "2006-03-01",
      "open": 62.01,
      "high": 66.7,
      "low": 59.91,
      "close": 66.25,
      "roc12": 19.78
    },
    {
      "month": "2006-04",
      "date": "2006-04-01",
      "open": 66.07,
      "high": 73.73,
      "low": 65.75,
      "close": 71.8,
      "roc12": 45.93
    },
    {
      "month": "2006-05",
      "date": "2006-05-01",
      "open": 73.75,
      "high": 74.62,
      "low": 68.44,
      "close": 71.42,
      "roc12": 37.14
    },
    {
      "month": "2006-06",
      "date": "2006-06-01",
      "open": 70.11,
      "high": 73.94,
      "low": 68.48,
      "close": 73.94,
      "roc12": 30.57
    },
    {
      "month": "2006-07",
      "date": "2006-07-01",
      "open": 75.2,
      "high": 76.8,
      "low": 72.79,
      "close": 74.56,
      "roc12": 22.81
    },
    {
      "month": "2006-08",
      "date": "2006-08-01",
      "open": 74.93,
      "high": 77.05,
      "low": 69.74,
      "close": 70.38,
      "roc12": 2.55
    },
    {
      "month": "2006-09",
      "date": "2006-09-01",
      "open": 69.24,
      "high": 69.24,
      "low": 59.79,
      "close": 62.9,
      "roc12": -5
    },
    {
      "month": "2006-10",
      "date": "2006-10-01",
      "open": 60.96,
      "high": 60.96,
      "low": 56.74,
      "close": 58.72,
      "roc12": -1.81
    },
    {
      "month": "2006-11",
      "date": "2006-11-01",
      "open": 58.64,
      "high": 62.97,
      "low": 55.9,
      "close": 62.97,
      "roc12": 9.84
    },
    {
      "month": "2006-12",
      "date": "2006-12-01",
      "open": 63.43,
      "high": 63.43,
      "low": 60.31,
      "close": 60.85,
      "roc12": -0.34
    },
    {
      "month": "2007-01",
      "date": "2007-01-01",
      "open": 60.77,
      "high": 60.77,
      "low": 50.51,
      "close": 58.17,
      "roc12": -14.28
    },
    {
      "month": "2007-02",
      "date": "2007-02-01",
      "open": 57.35,
      "high": 61.78,
      "low": 57.35,
      "close": 61.78,
      "roc12": 0.67
    },
    {
      "month": "2007-03",
      "date": "2007-03-01",
      "open": 61.97,
      "high": 66.1,
      "low": 56.41,
      "close": 65.94,
      "roc12": -0.47
    },
    {
      "month": "2007-04",
      "date": "2007-04-01",
      "open": 66.03,
      "high": 66.45,
      "low": 61.51,
      "close": 65.78,
      "roc12": -8.38
    },
    {
      "month": "2007-05",
      "date": "2007-05-01",
      "open": 64.43,
      "high": 66.25,
      "low": 61.48,
      "close": 64.02,
      "roc12": -10.36
    },
    {
      "month": "2007-06",
      "date": "2007-06-01",
      "open": 65.09,
      "high": 70.47,
      "low": 64.78,
      "close": 70.47,
      "roc12": -4.69
    },
    {
      "month": "2007-07",
      "date": "2007-07-01",
      "open": 71.11,
      "high": 78.2,
      "low": 71.11,
      "close": 78.2,
      "roc12": 4.88
    },
    {
      "month": "2007-08",
      "date": "2007-08-01",
      "open": 76.49,
      "high": 76.84,
      "low": 69.3,
      "close": 73.98,
      "roc12": 5.12
    },
    {
      "month": "2007-09",
      "date": "2007-09-01",
      "open": 75.07,
      "high": 83.85,
      "low": 75.07,
      "close": 81.64,
      "roc12": 29.79
    },
    {
      "month": "2007-10",
      "date": "2007-10-01",
      "open": 80.31,
      "high": 94.16,
      "low": 78.97,
      "close": 94.16,
      "roc12": 60.35
    },
    {
      "month": "2007-11",
      "date": "2007-11-01",
      "open": 93.53,
      "high": 99.16,
      "low": 88.6,
      "close": 88.6,
      "roc12": 40.7
    },
    {
      "month": "2007-12",
      "date": "2007-12-01",
      "open": 89.29,
      "high": 96.63,
      "low": 87.45,
      "close": 95.95,
      "roc12": 57.68
    },
    {
      "month": "2008-01",
      "date": "2008-01-01",
      "open": 99.64,
      "high": 99.64,
      "low": 87.65,
      "close": 91.67,
      "roc12": 57.59
    },
    {
      "month": "2008-02",
      "date": "2008-02-01",
      "open": 89.03,
      "high": 102.6,
      "low": 87.16,
      "close": 101.78,
      "roc12": 64.75
    },
    {
      "month": "2008-03",
      "date": "2008-03-01",
      "open": 102.42,
      "high": 110.21,
      "low": 99.72,
      "close": 101.54,
      "roc12": 53.99
    },
    {
      "month": "2008-04",
      "date": "2008-04-01",
      "open": 100.92,
      "high": 119.64,
      "low": 100.92,
      "close": 113.7,
      "roc12": 72.85
    },
    {
      "month": "2008-05",
      "date": "2008-05-01",
      "open": 112.6,
      "high": 132.99,
      "low": 112.6,
      "close": 127.35,
      "roc12": 98.92
    },
    {
      "month": "2008-06",
      "date": "2008-06-01",
      "open": 127.75,
      "high": 139.96,
      "low": 122.3,
      "close": 139.96,
      "roc12": 98.61
    },
    {
      "month": "2008-07",
      "date": "2008-07-01",
      "open": 141.06,
      "high": 145.31,
      "low": 122.21,
      "close": 124.17,
      "roc12": 58.79
    },
    {
      "month": "2008-08",
      "date": "2008-08-01",
      "open": 125.03,
      "high": 125.03,
      "low": 112.92,
      "close": 115.55,
      "roc12": 56.19
    },
    {
      "month": "2008-09",
      "date": "2008-09-01",
      "open": 109.63,
      "high": 122.61,
      "low": 91.49,
      "close": 100.7,
      "roc12": 23.35
    },
    {
      "month": "2008-10",
      "date": "2008-10-01",
      "open": 98.23,
      "high": 98.23,
      "low": 61.92,
      "close": 68.1,
      "roc12": -27.68
    },
    {
      "month": "2008-11",
      "date": "2008-11-01",
      "open": 63.93,
      "high": 70.41,
      "low": 48.86,
      "close": 55.21,
      "roc12": -37.69
    },
    {
      "month": "2008-12",
      "date": "2008-12-01",
      "open": 49.34,
      "high": 49.34,
      "low": 30.28,
      "close": 44.6,
      "roc12": -53.52
    },
    {
      "month": "2009-01",
      "date": "2009-01-01",
      "open": 46.17,
      "high": 48.61,
      "low": 35.38,
      "close": 41.73,
      "roc12": -54.48
    },
    {
      "month": "2009-02",
      "date": "2009-02-01",
      "open": 41.35,
      "high": 44.15,
      "low": 34.03,
      "close": 44.15,
      "roc12": -56.62
    },
    {
      "month": "2009-03",
      "date": "2009-03-01",
      "open": 40.07,
      "high": 53.87,
      "low": 40.07,
      "close": 49.64,
      "roc12": -51.11
    },
    {
      "month": "2009-04",
      "date": "2009-04-01",
      "open": 48.46,
      "high": 52.61,
      "low": 45.82,
      "close": 50.35,
      "roc12": -55.72
    },
    {
      "month": "2009-05",
      "date": "2009-05-01",
      "open": 52.18,
      "high": 66.31,
      "low": 52.18,
      "close": 66.31,
      "roc12": -47.93
    },
    {
      "month": "2009-06",
      "date": "2009-06-01",
      "open": 68.59,
      "high": 72.69,
      "low": 66.14,
      "close": 69.82,
      "roc12": -50.11
    },
    {
      "month": "2009-07",
      "date": "2009-07-01",
      "open": 69.32,
      "high": 69.32,
      "low": 59.62,
      "close": 69.26,
      "roc12": -44.22
    },
    {
      "month": "2009-08",
      "date": "2009-08-01",
      "open": 71.59,
      "high": 73.68,
      "low": 66.72,
      "close": 69.97,
      "roc12": -39.45
    },
    {
      "month": "2009-09",
      "date": "2009-09-01",
      "open": 68.11,
      "high": 72.5,
      "low": 65.74,
      "close": 70.46,
      "roc12": -30.03
    },
    {
      "month": "2009-10",
      "date": "2009-10-01",
      "open": 70.67,
      "high": 81.03,
      "low": 69.6,
      "close": 77.04,
      "roc12": 13.13
    },
    {
      "month": "2009-11",
      "date": "2009-11-01",
      "open": 78.08,
      "high": 80.3,
      "low": 74.88,
      "close": 77.19,
      "roc12": 39.81
    },
    {
      "month": "2009-12",
      "date": "2009-12-01",
      "open": 78.39,
      "high": 79.39,
      "low": 69.48,
      "close": 79.39,
      "roc12": 78
    },
    {
      "month": "2010-01",
      "date": "2010-01-01",
      "open": 81.52,
      "high": 83.12,
      "low": 72.85,
      "close": 72.85,
      "roc12": 74.57
    },
    {
      "month": "2010-02",
      "date": "2010-02-01",
      "open": 74.41,
      "high": 80.04,
      "low": 71.15,
      "close": 79.72,
      "roc12": 80.57
    },
    {
      "month": "2010-03",
      "date": "2010-03-01",
      "open": 78.71,
      "high": 83.45,
      "low": 78.71,
      "close": 83.45,
      "roc12": 68.11
    },
    {
      "month": "2010-04",
      "date": "2010-04-01",
      "open": 84.53,
      "high": 86.54,
      "low": 81.52,
      "close": 86.07,
      "roc12": 70.94
    },
    {
      "month": "2010-05",
      "date": "2010-05-01",
      "open": 86.19,
      "high": 86.19,
      "low": 64.78,
      "close": 74,
      "roc12": 11.6
    },
    {
      "month": "2010-06",
      "date": "2010-06-01",
      "open": 72.7,
      "high": 78.45,
      "low": 71.43,
      "close": 75.59,
      "roc12": 8.26
    },
    {
      "month": "2010-07",
      "date": "2010-07-01",
      "open": 72.95,
      "high": 79.01,
      "low": 71.96,
      "close": 78.85,
      "roc12": 13.85
    },
    {
      "month": "2010-08",
      "date": "2010-08-01",
      "open": 81.25,
      "high": 82.52,
      "low": 71.24,
      "close": 71.93,
      "roc12": 2.8
    },
    {
      "month": "2010-09",
      "date": "2010-09-01",
      "open": 73.97,
      "high": 79.95,
      "low": 72.96,
      "close": 79.95,
      "roc12": 13.47
    },
    {
      "month": "2010-10",
      "date": "2010-10-01",
      "open": 81.57,
      "high": 83.21,
      "low": 79.57,
      "close": 81.45,
      "roc12": 5.72
    },
    {
      "month": "2010-11",
      "date": "2010-11-01",
      "open": 82.94,
      "high": 87.77,
      "low": 80.43,
      "close": 84.12,
      "roc12": 8.98
    },
    {
      "month": "2010-12",
      "date": "2010-12-01",
      "open": 86.75,
      "high": 91.48,
      "low": 86.75,
      "close": 91.38,
      "roc12": 15.1
    },
    {
      "month": "2011-01",
      "date": "2011-01-01",
      "open": 91.59,
      "high": 91.85,
      "low": 84.45,
      "close": 90.99,
      "roc12": 24.9
    },
    {
      "month": "2011-02",
      "date": "2011-02-01",
      "open": 89.54,
      "high": 97.1,
      "low": 83.13,
      "close": 97.1,
      "roc12": 21.8
    },
    {
      "month": "2011-03",
      "date": "2011-03-01",
      "open": 99.63,
      "high": 106.19,
      "low": 97.23,
      "close": 106.19,
      "roc12": 27.25
    },
    {
      "month": "2011-04",
      "date": "2011-04-01",
      "open": 107.55,
      "high": 113.39,
      "low": 105.75,
      "close": 113.39,
      "roc12": 31.74
    },
    {
      "month": "2011-05",
      "date": "2011-05-01",
      "open": 113.03,
      "high": 113.03,
      "low": 96.4,
      "close": 102.7,
      "roc12": 38.78
    },
    {
      "month": "2011-06",
      "date": "2011-06-01",
      "open": 100.3,
      "high": 101.95,
      "low": 90.65,
      "close": 95.3,
      "roc12": 26.07
    },
    {
      "month": "2011-07",
      "date": "2011-07-01",
      "open": 94.81,
      "high": 99.61,
      "low": 94.81,
      "close": 95.68,
      "roc12": 21.34
    },
    {
      "month": "2011-08",
      "date": "2011-08-01",
      "open": 94.98,
      "high": 94.98,
      "low": 79.32,
      "close": 88.81,
      "roc12": 23.47
    },
    {
      "month": "2011-09",
      "date": "2011-09-01",
      "open": 88.93,
      "high": 90.21,
      "low": 78.93,
      "close": 78.93,
      "roc12": -1.28
    },
    {
      "month": "2011-10",
      "date": "2011-10-01",
      "open": 77.34,
      "high": 93.96,
      "low": 75.4,
      "close": 93.19,
      "roc12": 14.41
    },
    {
      "month": "2011-11",
      "date": "2011-11-01",
      "open": 92.19,
      "high": 102.59,
      "low": 92.19,
      "close": 100.36,
      "roc12": 19.31
    },
    {
      "month": "2011-12",
      "date": "2011-12-01",
      "open": 100.2,
      "high": 101.29,
      "low": 93.55,
      "close": 98.83,
      "roc12": 8.15
    },
    {
      "month": "2012-01",
      "date": "2012-01-01",
      "open": 102.96,
      "high": 103.22,
      "low": 98.15,
      "close": 98.46,
      "roc12": 8.21
    },
    {
      "month": "2012-02",
      "date": "2012-02-01",
      "open": 97.63,
      "high": 109.39,
      "low": 96.36,
      "close": 107.08,
      "roc12": 10.28
    },
    {
      "month": "2012-03",
      "date": "2012-03-01",
      "open": 108.76,
      "high": 108.76,
      "low": 102.79,
      "close": 103.03,
      "roc12": -2.98
    },
    {
      "month": "2012-04",
      "date": "2012-04-01",
      "open": 105.25,
      "high": 105.25,
      "low": 101.12,
      "close": 104.89,
      "roc12": -7.5
    },
    {
      "month": "2012-05",
      "date": "2012-05-01",
      "open": 106.17,
      "high": 106.17,
      "low": 86.52,
      "close": 86.52,
      "roc12": -15.75
    },
    {
      "month": "2012-06",
      "date": "2012-06-01",
      "open": 83.17,
      "high": 85.05,
      "low": 77.72,
      "close": 85.04,
      "roc12": -10.77
    },
    {
      "month": "2012-07",
      "date": "2012-07-01",
      "open": 83.72,
      "high": 92.78,
      "low": 83.72,
      "close": 88.08,
      "roc12": -7.94
    },
    {
      "month": "2012-08",
      "date": "2012-08-01",
      "open": 88.99,
      "high": 96.89,
      "low": 87.22,
      "close": 96.47,
      "roc12": 8.63
    },
    {
      "month": "2012-09",
      "date": "2012-09-01",
      "open": 95.34,
      "high": 98.94,
      "low": 89.92,
      "close": 92.18,
      "roc12": 16.79
    },
    {
      "month": "2012-10",
      "date": "2012-10-01",
      "open": 92.44,
      "high": 92.44,
      "low": 85.39,
      "close": 86.23,
      "roc12": -7.47
    },
    {
      "month": "2012-11",
      "date": "2012-11-01",
      "open": 87.05,
      "high": 89.05,
      "low": 84.5,
      "close": 88.54,
      "roc12": -11.78
    },
    {
      "month": "2012-12",
      "date": "2012-12-01",
      "open": 88.69,
      "high": 91.83,
      "low": 85.14,
      "close": 91.83,
      "roc12": -7.08
    },
    {
      "month": "2013-01",
      "date": "2013-01-01",
      "open": 93.14,
      "high": 97.98,
      "low": 92.97,
      "close": 97.65,
      "roc12": -0.82
    },
    {
      "month": "2013-02",
      "date": "2013-02-01",
      "open": 97.46,
      "high": 97.48,
      "low": 92.03,
      "close": 92.03,
      "roc12": -14.05
    },
    {
      "month": "2013-03",
      "date": "2013-03-01",
      "open": 90.71,
      "high": 97.24,
      "low": 90.13,
      "close": 97.24,
      "roc12": -5.62
    },
    {
      "month": "2013-04",
      "date": "2013-04-01",
      "open": 97.1,
      "high": 97.23,
      "low": 86.65,
      "close": 93.22,
      "roc12": -11.13
    },
    {
      "month": "2013-05",
      "date": "2013-05-01",
      "open": 90.74,
      "high": 96.29,
      "low": 90.74,
      "close": 91.93,
      "roc12": 6.25
    },
    {
      "month": "2013-06",
      "date": "2013-06-01",
      "open": 93.41,
      "high": 98.46,
      "low": 93.36,
      "close": 96.36,
      "roc12": 13.31
    },
    {
      "month": "2013-07",
      "date": "2013-07-01",
      "open": 97.94,
      "high": 108,
      "low": 97.94,
      "close": 105.1,
      "roc12": 19.32
    },
    {
      "month": "2013-08",
      "date": "2013-08-01",
      "open": 107.93,
      "high": 110.17,
      "low": 103.45,
      "close": 107.98,
      "roc12": 11.93
    },
    {
      "month": "2013-09",
      "date": "2013-09-01",
      "open": 108.67,
      "high": 110.62,
      "low": 102.36,
      "close": 102.36,
      "roc12": 11.04
    },
    {
      "month": "2013-10",
      "date": "2013-10-01",
      "open": 102.09,
      "high": 104.15,
      "low": 96.29,
      "close": 96.29,
      "roc12": 11.67
    },
    {
      "month": "2013-11",
      "date": "2013-11-01",
      "open": 94.56,
      "high": 95.35,
      "low": 92.05,
      "close": 92.55,
      "roc12": 4.53
    },
    {
      "month": "2013-12",
      "date": "2013-12-01",
      "open": 93.61,
      "high": 99.94,
      "low": 93.61,
      "close": 98.17,
      "roc12": 6.9
    },
    {
      "month": "2014-01",
      "date": "2014-01-01",
      "open": 95.14,
      "high": 98.25,
      "low": 91.36,
      "close": 97.55,
      "roc12": -0.1
    },
    {
      "month": "2014-02",
      "date": "2014-02-01",
      "open": 96.44,
      "high": 103.46,
      "low": 96.44,
      "close": 102.88,
      "roc12": 11.79
    },
    {
      "month": "2014-03",
      "date": "2014-03-01",
      "open": 105.34,
      "high": 105.34,
      "low": 98.29,
      "close": 101.57,
      "roc12": 4.45
    },
    {
      "month": "2014-04",
      "date": "2014-04-01",
      "open": 99.69,
      "high": 104.35,
      "low": 99.6,
      "close": 100.07,
      "roc12": 7.35
    },
    {
      "month": "2014-05",
      "date": "2014-05-01",
      "open": 99.69,
      "high": 105.01,
      "low": 99.69,
      "close": 103.4,
      "roc12": 12.48
    },
    {
      "month": "2014-06",
      "date": "2014-06-01",
      "open": 103.07,
      "high": 107.95,
      "low": 103.07,
      "close": 106.07,
      "roc12": 10.08
    },
    {
      "month": "2014-07",
      "date": "2014-07-01",
      "open": 106.06,
      "high": 106.06,
      "low": 98.23,
      "close": 98.23,
      "roc12": -6.54
    },
    {
      "month": "2014-08",
      "date": "2014-08-01",
      "open": 97.86,
      "high": 98.26,
      "low": 93.61,
      "close": 97.86,
      "roc12": -9.37
    },
    {
      "month": "2014-09",
      "date": "2014-09-01",
      "open": 92.92,
      "high": 95.55,
      "low": 91.17,
      "close": 91.17,
      "roc12": -10.93
    },
    {
      "month": "2014-10",
      "date": "2014-10-01",
      "open": 90.74,
      "high": 91.02,
      "low": 80.52,
      "close": 80.53,
      "roc12": -16.37
    },
    {
      "month": "2014-11",
      "date": "2014-11-01",
      "open": 78.77,
      "high": 78.77,
      "low": 65.94,
      "close": 65.94,
      "roc12": -28.75
    },
    {
      "month": "2014-12",
      "date": "2014-12-01",
      "open": 68.98,
      "high": 68.98,
      "low": 53.45,
      "close": 53.45,
      "roc12": -45.55
    },
    {
      "month": "2015-01",
      "date": "2015-01-01",
      "open": 52.72,
      "high": 52.72,
      "low": 44.08,
      "close": 47.79,
      "roc12": -51.01
    },
    {
      "month": "2015-02",
      "date": "2015-02-01",
      "open": 49.25,
      "high": 53.56,
      "low": 47.65,
      "close": 49.84,
      "roc12": -51.56
    },
    {
      "month": "2015-03",
      "date": "2015-03-01",
      "open": 49.59,
      "high": 51.53,
      "low": 43.39,
      "close": 47.72,
      "roc12": -53.02
    },
    {
      "month": "2015-04",
      "date": "2015-04-01",
      "open": 50.12,
      "high": 59.62,
      "low": 49.13,
      "close": 59.62,
      "roc12": -40.42
    },
    {
      "month": "2015-05",
      "date": "2015-05-01",
      "open": 59.1,
      "high": 60.93,
      "low": 57.29,
      "close": 60.25,
      "roc12": -41.73
    },
    {
      "month": "2015-06",
      "date": "2015-06-01",
      "open": 60.24,
      "high": 61.36,
      "low": 58,
      "close": 59.48,
      "roc12": -43.92
    },
    {
      "month": "2015-07",
      "date": "2015-07-01",
      "open": 56.94,
      "high": 56.94,
      "low": 47.11,
      "close": 47.11,
      "roc12": -52.04
    },
    {
      "month": "2015-08",
      "date": "2015-08-01",
      "open": 45.25,
      "high": 49.2,
      "low": 38.22,
      "close": 49.2,
      "roc12": -49.72
    },
    {
      "month": "2015-09",
      "date": "2015-09-01",
      "open": 45.38,
      "high": 47.12,
      "low": 44.07,
      "close": 45.06,
      "roc12": -50.58
    },
    {
      "month": "2015-10",
      "date": "2015-10-01",
      "open": 44.75,
      "high": 49.67,
      "low": 43.19,
      "close": 46.6,
      "roc12": -42.13
    },
    {
      "month": "2015-11",
      "date": "2015-11-01",
      "open": 46.12,
      "high": 47.88,
      "low": 39.27,
      "close": 40.43,
      "roc12": -38.69
    },
    {
      "month": "2015-12",
      "date": "2015-12-01",
      "open": 40.58,
      "high": 41.08,
      "low": 34.55,
      "close": 37.13,
      "roc12": -30.53
    },
    {
      "month": "2016-01",
      "date": "2016-01-01",
      "open": 36.81,
      "high": 36.81,
      "low": 26.68,
      "close": 33.66,
      "roc12": -29.57
    },
    {
      "month": "2016-02",
      "date": "2016-02-01",
      "open": 31.62,
      "high": 32.74,
      "low": 26.19,
      "close": 32.74,
      "roc12": -34.31
    },
    {
      "month": "2016-03",
      "date": "2016-03-01",
      "open": 34.39,
      "high": 41.45,
      "low": 34.39,
      "close": 36.94,
      "roc12": -22.59
    },
    {
      "month": "2016-04",
      "date": "2016-04-01",
      "open": 35.36,
      "high": 46.03,
      "low": 34.3,
      "close": 45.98,
      "roc12": -22.88
    },
    {
      "month": "2016-05",
      "date": "2016-05-01",
      "open": 44.75,
      "high": 49.36,
      "low": 43.45,
      "close": 49.1,
      "roc12": -18.51
    },
    {
      "month": "2016-06",
      "date": "2016-06-01",
      "open": 49.07,
      "high": 51.23,
      "low": 45.8,
      "close": 48.27,
      "roc12": -18.85
    },
    {
      "month": "2016-07",
      "date": "2016-07-01",
      "open": 49.02,
      "high": 49.02,
      "low": 41.13,
      "close": 41.54,
      "roc12": -11.82
    },
    {
      "month": "2016-08",
      "date": "2016-08-01",
      "open": 40.05,
      "high": 48.48,
      "low": 39.5,
      "close": 44.68,
      "roc12": -9.19
    },
    {
      "month": "2016-09",
      "date": "2016-09-01",
      "open": 43.17,
      "high": 47.72,
      "low": 43.04,
      "close": 47.72,
      "roc12": 5.9
    },
    {
      "month": "2016-10",
      "date": "2016-10-01",
      "open": 48.8,
      "high": 51.59,
      "low": 46.83,
      "close": 46.83,
      "roc12": 0.49
    },
    {
      "month": "2016-11",
      "date": "2016-11-01",
      "open": 46.66,
      "high": 49.41,
      "low": 43.29,
      "close": 49.41,
      "roc12": 22.21
    },
    {
      "month": "2016-12",
      "date": "2016-12-01",
      "open": 51.08,
      "high": 54.01,
      "low": 49.85,
      "close": 53.75,
      "roc12": 44.76
    },
    {
      "month": "2017-01",
      "date": "2017-01-01",
      "open": 52.36,
      "high": 53.98,
      "low": 50.82,
      "close": 52.75,
      "roc12": 56.71
    },
    {
      "month": "2017-02",
      "date": "2017-02-01",
      "open": 53.9,
      "high": 54.48,
      "low": 52.19,
      "close": 54,
      "roc12": 64.94
    },
    {
      "month": "2017-03",
      "date": "2017-03-01",
      "open": 53.82,
      "high": 53.82,
      "low": 47,
      "close": 50.54,
      "roc12": 36.82
    },
    {
      "month": "2017-04",
      "date": "2017-04-01",
      "open": 50.25,
      "high": 53.38,
      "low": 48.9,
      "close": 49.31,
      "roc12": 7.24
    },
    {
      "month": "2017-05",
      "date": "2017-05-01",
      "open": 48.83,
      "high": 51.12,
      "low": 45.55,
      "close": 48.29,
      "roc12": -1.65
    },
    {
      "month": "2017-06",
      "date": "2017-06-01",
      "open": 48.32,
      "high": 48.32,
      "low": 42.48,
      "close": 46.02,
      "roc12": -4.66
    },
    {
      "month": "2017-07",
      "date": "2017-07-01",
      "open": 45.11,
      "high": 50.21,
      "low": 44.25,
      "close": 50.21,
      "roc12": 20.87
    },
    {
      "month": "2017-08",
      "date": "2017-08-01",
      "open": 49.19,
      "high": 49.6,
      "low": 45.96,
      "close": 47.26,
      "roc12": 5.77
    },
    {
      "month": "2017-09",
      "date": "2017-09-01",
      "open": 47.32,
      "high": 52.14,
      "low": 47.32,
      "close": 51.67,
      "roc12": 8.28
    },
    {
      "month": "2017-10",
      "date": "2017-10-01",
      "open": 50.59,
      "high": 54.36,
      "low": 49.34,
      "close": 54.36,
      "roc12": 16.08
    },
    {
      "month": "2017-11",
      "date": "2017-11-01",
      "open": 54.32,
      "high": 58.94,
      "low": 54.32,
      "close": 57.4,
      "roc12": 16.17
    },
    {
      "month": "2017-12",
      "date": "2017-12-01",
      "open": 58.35,
      "high": 60.46,
      "low": 55.79,
      "close": 60.46,
      "roc12": 12.48
    },
    {
      "month": "2018-01",
      "date": "2018-01-01",
      "open": 60.37,
      "high": 66.27,
      "low": 60.37,
      "close": 64.82,
      "roc12": 22.88
    },
    {
      "month": "2018-02",
      "date": "2018-02-01",
      "open": 65.92,
      "high": 65.92,
      "low": 59.2,
      "close": 61.43,
      "roc12": 13.76
    },
    {
      "month": "2018-03",
      "date": "2018-03-01",
      "open": 60.98,
      "high": 65.8,
      "low": 60.13,
      "close": 64.87,
      "roc12": 28.35
    },
    {
      "month": "2018-04",
      "date": "2018-04-01",
      "open": 63.05,
      "high": 68.56,
      "low": 62.03,
      "close": 68.56,
      "roc12": 39.04
    },
    {
      "month": "2018-05",
      "date": "2018-05-01",
      "open": 67.28,
      "high": 72.26,
      "low": 66.8,
      "close": 66.98,
      "roc12": 38.7
    },
    {
      "month": "2018-06",
      "date": "2018-06-01",
      "open": 65.81,
      "high": 77.41,
      "low": 64.75,
      "close": 74.13,
      "roc12": 61.08
    },
    {
      "month": "2018-07",
      "date": "2018-07-01",
      "open": 73.89,
      "high": 74.19,
      "low": 67.9,
      "close": 69.88,
      "roc12": 39.18
    },
    {
      "month": "2018-08",
      "date": "2018-08-01",
      "open": 68.8,
      "high": 70.25,
      "low": 65.07,
      "close": 69.84,
      "roc12": 47.78
    },
    {
      "month": "2018-09",
      "date": "2018-09-01",
      "open": 69.82,
      "high": 73.4,
      "low": 67.55,
      "close": 73.16,
      "roc12": 41.59
    },
    {
      "month": "2018-10",
      "date": "2018-10-01",
      "open": 75.37,
      "high": 76.4,
      "low": 65.31,
      "close": 65.31,
      "roc12": 20.14
    },
    {
      "month": "2018-11",
      "date": "2018-11-01",
      "open": 63.67,
      "high": 63.67,
      "low": 50.06,
      "close": 50.78,
      "roc12": -11.53
    },
    {
      "month": "2018-12",
      "date": "2018-12-01",
      "open": 52.98,
      "high": 53.21,
      "low": 44.48,
      "close": 45.15,
      "roc12": -25.32
    },
    {
      "month": "2019-01",
      "date": "2019-01-01",
      "open": 46.31,
      "high": 54.18,
      "low": 46.31,
      "close": 53.84,
      "roc12": -16.94
    },
    {
      "month": "2019-02",
      "date": "2019-02-01",
      "open": 55.29,
      "high": 57.21,
      "low": 52.43,
      "close": 57.21,
      "roc12": -6.87
    },
    {
      "month": "2019-03",
      "date": "2019-03-01",
      "open": 55.76,
      "high": 60.19,
      "low": 55.76,
      "close": 60.19,
      "roc12": -7.21
    },
    {
      "month": "2019-04",
      "date": "2019-04-01",
      "open": 61.59,
      "high": 66.24,
      "low": 61.59,
      "close": 63.83,
      "roc12": -6.9
    },
    {
      "month": "2019-05",
      "date": "2019-05-01",
      "open": 63.55,
      "high": 63.55,
      "low": 53.49,
      "close": 53.49,
      "roc12": -20.14
    },
    {
      "month": "2019-06",
      "date": "2019-06-01",
      "open": 53.25,
      "high": 59.18,
      "low": 51.13,
      "close": 58.2,
      "roc12": -21.49
    },
    {
      "month": "2019-07",
      "date": "2019-07-01",
      "open": 58.91,
      "high": 60.28,
      "low": 55.08,
      "close": 58.53,
      "roc12": -16.24
    },
    {
      "month": "2019-08",
      "date": "2019-08-01",
      "open": 53.64,
      "high": 57.05,
      "low": 51.14,
      "close": 55.07,
      "roc12": -21.15
    },
    {
      "month": "2019-09",
      "date": "2019-09-01",
      "open": 53.91,
      "high": 63.1,
      "low": 53.91,
      "close": 54.09,
      "roc12": -26.07
    },
    {
      "month": "2019-10",
      "date": "2019-10-01",
      "open": 53.6,
      "high": 56.52,
      "low": 52.41,
      "close": 54.02,
      "roc12": -17.29
    },
    {
      "month": "2019-11",
      "date": "2019-11-01",
      "open": 56.04,
      "high": 58.36,
      "low": 54.93,
      "close": 58.12,
      "roc12": 14.45
    },
    {
      "month": "2019-12",
      "date": "2019-12-01",
      "open": 55.97,
      "high": 61.76,
      "low": 55.97,
      "close": 61.14,
      "roc12": 35.42
    },
    {
      "month": "2020-01",
      "date": "2020-01-01",
      "open": 61.17,
      "high": 63.27,
      "low": 51.58,
      "close": 51.58,
      "roc12": -4.2
    },
    {
      "month": "2020-02",
      "date": "2020-02-01",
      "open": 50.06,
      "high": 53.77,
      "low": 44.83,
      "close": 44.83,
      "roc12": -21.64
    },
    {
      "month": "2020-03",
      "date": "2020-03-01",
      "open": 46.78,
      "high": 47.27,
      "low": 14.1,
      "close": 20.51,
      "roc12": -65.92
    },
    {
      "month": "2020-04",
      "date": "2020-04-01",
      "open": 20.28,
      "high": 28.36,
      "low": 8.91,
      "close": 19.23,
      "roc12": -69.87
    },
    {
      "month": "2020-05",
      "date": "2020-05-01",
      "open": 19.72,
      "high": 35.57,
      "low": 19.72,
      "close": 35.57,
      "roc12": -33.5
    },
    {
      "month": "2020-06",
      "date": "2020-06-01",
      "open": 35.49,
      "high": 40.6,
      "low": 35.49,
      "close": 39.27,
      "roc12": -32.53
    },
    {
      "month": "2020-07",
      "date": "2020-07-01",
      "open": 39.88,
      "high": 41.88,
      "low": 39.64,
      "close": 40.1,
      "roc12": -31.49
    },
    {
      "month": "2020-08",
      "date": "2020-08-01",
      "open": 40.83,
      "high": 43.21,
      "low": 40.83,
      "close": 42.61,
      "roc12": -22.63
    },
    {
      "month": "2020-09",
      "date": "2020-09-01",
      "open": 42.76,
      "high": 42.76,
      "low": 36.87,
      "close": 40.05,
      "roc12": -25.96
    },
    {
      "month": "2020-10",
      "date": "2020-10-01",
      "open": 38.51,
      "high": 41.37,
      "low": 35.64,
      "close": 35.64,
      "roc12": -34.02
    },
    {
      "month": "2020-11",
      "date": "2020-11-01",
      "open": 36.6,
      "high": 45.58,
      "low": 36.6,
      "close": 45.2,
      "roc12": -22.23
    },
    {
      "month": "2020-12",
      "date": "2020-12-01",
      "open": 44.54,
      "high": 49.04,
      "low": 44.54,
      "close": 48.35,
      "roc12": -20.92
    },
    {
      "month": "2021-01",
      "date": "2021-01-01",
      "open": 47.47,
      "high": 53.47,
      "low": 47.47,
      "close": 52.16,
      "roc12": 1.12
    },
    {
      "month": "2021-02",
      "date": "2021-02-01",
      "open": 53.55,
      "high": 63.43,
      "low": 53.55,
      "close": 61.55,
      "roc12": 37.3
    },
    {
      "month": "2021-03",
      "date": "2021-03-01",
      "open": 60.54,
      "high": 66.08,
      "low": 57.75,
      "close": 59.19,
      "roc12": 188.59
    },
    {
      "month": "2021-04",
      "date": "2021-04-01",
      "open": 61.41,
      "high": 65,
      "low": 58.73,
      "close": 63.5,
      "roc12": 230.21
    },
    {
      "month": "2021-05",
      "date": "2021-05-01",
      "open": 64.46,
      "high": 66.87,
      "low": 61.95,
      "close": 66.31,
      "roc12": 86.42
    },
    {
      "month": "2021-06",
      "date": "2021-06-01",
      "open": 67.8,
      "high": 74.21,
      "low": 67.8,
      "close": 73.52,
      "roc12": 87.22
    },
    {
      "month": "2021-07",
      "date": "2021-07-01",
      "open": 75.33,
      "high": 75.37,
      "low": 66.45,
      "close": 73.93,
      "roc12": 84.36
    },
    {
      "month": "2021-08",
      "date": "2021-08-01",
      "open": 71.31,
      "high": 71.31,
      "low": 62.25,
      "close": 68.43,
      "roc12": 60.6
    },
    {
      "month": "2021-09",
      "date": "2021-09-01",
      "open": 68.63,
      "high": 75.54,
      "low": 68.26,
      "close": 75.22,
      "roc12": 87.82
    },
    {
      "month": "2021-10",
      "date": "2021-10-01",
      "open": 76.01,
      "high": 85.64,
      "low": 76.01,
      "close": 83.5,
      "roc12": 134.29
    },
    {
      "month": "2021-11",
      "date": "2021-11-01",
      "open": 84.08,
      "high": 84.12,
      "low": 66.14,
      "close": 66.14,
      "roc12": 46.33
    },
    {
      "month": "2021-12",
      "date": "2021-12-01",
      "open": 65.44,
      "high": 76.83,
      "low": 65.44,
      "close": 75.33,
      "roc12": 55.8
    },
    {
      "month": "2022-01",
      "date": "2022-01-01",
      "open": 75.99,
      "high": 89.16,
      "low": 75.99,
      "close": 89.16,
      "roc12": 70.94
    },
    {
      "month": "2022-02",
      "date": "2022-02-01",
      "open": 88.22,
      "high": 96.13,
      "low": 88.16,
      "close": 96.13,
      "roc12": 56.18
    },
    {
      "month": "2022-03",
      "date": "2022-03-01",
      "open": 103.66,
      "high": 123.64,
      "low": 94.85,
      "close": 100.53,
      "roc12": 69.84
    },
    {
      "month": "2022-04",
      "date": "2022-04-01",
      "open": 99.32,
      "high": 108.24,
      "low": 94.22,
      "close": 104.59,
      "roc12": 64.71
    },
    {
      "month": "2022-05",
      "date": "2022-05-01",
      "open": 105.18,
      "high": 116.19,
      "low": 99.74,
      "close": 114.38,
      "roc12": 72.49
    },
    {
      "month": "2022-06",
      "date": "2022-06-01",
      "open": 115.26,
      "high": 121.94,
      "low": 105.75,
      "close": 107.76,
      "roc12": 46.57
    },
    {
      "month": "2022-07",
      "date": "2022-07-01",
      "open": 110.3,
      "high": 110.3,
      "low": 97.69,
      "close": 101.31,
      "roc12": 37.04
    },
    {
      "month": "2022-08",
      "date": "2022-08-01",
      "open": 96.59,
      "high": 97.4,
      "low": 89.23,
      "close": 90.09,
      "roc12": 31.65
    },
    {
      "month": "2022-09",
      "date": "2022-09-01",
      "open": 87.09,
      "high": 88.88,
      "low": 77.17,
      "close": 79.91,
      "roc12": 6.24
    },
    {
      "month": "2022-10",
      "date": "2022-10-01",
      "open": 84.05,
      "high": 93.07,
      "low": 83.29,
      "close": 86.54,
      "roc12": 3.64
    },
    {
      "month": "2022-11",
      "date": "2022-11-01",
      "open": 88.36,
      "high": 92.58,
      "low": 76.45,
      "close": 80.48,
      "roc12": 21.68
    },
    {
      "month": "2022-12",
      "date": "2022-12-01",
      "open": 81.06,
      "high": 81.06,
      "low": 71.05,
      "close": 80.16,
      "roc12": 6.41
    },
    {
      "month": "2023-01",
      "date": "2023-01-01",
      "open": 76.87,
      "high": 81.62,
      "low": 72.82,
      "close": 78.95,
      "roc12": -11.45
    },
    {
      "month": "2023-02",
      "date": "2023-02-01",
      "open": 76.34,
      "high": 80.14,
      "low": 73.4,
      "close": 76.88,
      "roc12": -20.02
    },
    {
      "month": "2023-03",
      "date": "2023-03-01",
      "open": 77.57,
      "high": 80.39,
      "low": 66.61,
      "close": 75.68,
      "roc12": -24.72
    },
    {
      "month": "2023-04",
      "date": "2023-04-01",
      "open": 80.4,
      "high": 83.26,
      "low": 74.33,
      "close": 76.78,
      "roc12": -26.59
    },
    {
      "month": "2023-05",
      "date": "2023-05-01",
      "open": 75.65,
      "high": 75.65,
      "low": 68.11,
      "close": 68.11,
      "roc12": -40.45
    },
    {
      "month": "2023-06",
      "date": "2023-06-01",
      "open": 70.09,
      "high": 72.55,
      "low": 67.08,
      "close": 70.66,
      "roc12": -34.43
    },
    {
      "month": "2023-07",
      "date": "2023-07-01",
      "open": 69.71,
      "high": 81.8,
      "low": 69.71,
      "close": 81.8,
      "roc12": -19.26
    },
    {
      "month": "2023-08",
      "date": "2023-08-01",
      "open": 81.37,
      "high": 84.35,
      "low": 78.91,
      "close": 83.55,
      "roc12": -7.26
    },
    {
      "month": "2023-09",
      "date": "2023-09-01",
      "open": 85.52,
      "high": 93.67,
      "low": 85.52,
      "close": 90.77,
      "roc12": 13.59
    },
    {
      "month": "2023-10",
      "date": "2023-10-01",
      "open": 88.81,
      "high": 89.35,
      "low": 81.64,
      "close": 81.64,
      "roc12": -5.66
    },
    {
      "month": "2023-11",
      "date": "2023-11-01",
      "open": 81.05,
      "high": 83.04,
      "low": 73.5,
      "close": 75.66,
      "roc12": -5.99
    },
    {
      "month": "2023-12",
      "date": "2023-12-01",
      "open": 73.7,
      "high": 75.84,
      "low": 68.27,
      "close": 71.89,
      "roc12": -10.32
    },
    {
      "month": "2024-01",
      "date": "2024-01-01",
      "open": 70.62,
      "high": 78.45,
      "low": 70.62,
      "close": 76.28,
      "roc12": -3.38
    },
    {
      "month": "2024-02",
      "date": "2024-02-01",
      "open": 74.36,
      "high": 79.8,
      "low": 72.72,
      "close": 79.22,
      "roc12": 3.04
    },
    {
      "month": "2024-03",
      "date": "2024-03-01",
      "open": 80.9,
      "high": 84.39,
      "low": 78.51,
      "close": 83.96,
      "roc12": 10.94
    },
    {
      "month": "2024-04",
      "date": "2024-04-01",
      "open": 84.54,
      "high": 87.69,
      "low": 83.49,
      "close": 83.49,
      "roc12": 8.74
    },
    {
      "month": "2024-05",
      "date": "2024-05-01",
      "open": 80.7,
      "high": 81.66,
      "low": 77.47,
      "close": 77.97,
      "roc12": 14.48
    },
    {
      "month": "2024-06",
      "date": "2024-06-01",
      "open": 75.26,
      "high": 83.34,
      "low": 74.27,
      "close": 82.83,
      "roc12": 17.22
    },
    {
      "month": "2024-07",
      "date": "2024-07-01",
      "open": 84.7,
      "high": 85.19,
      "low": 76.17,
      "close": 79.36,
      "roc12": -2.98
    },
    {
      "month": "2024-08",
      "date": "2024-08-01",
      "open": 77.74,
      "high": 81.45,
      "low": 72.76,
      "close": 74.52,
      "roc12": -10.81
    },
    {
      "month": "2024-09",
      "date": "2024-09-01",
      "open": 71.28,
      "high": 72.86,
      "low": 66.73,
      "close": 68.75,
      "roc12": -24.26
    },
    {
      "month": "2024-10",
      "date": "2024-10-01",
      "open": 70.41,
      "high": 77.76,
      "low": 67.48,
      "close": 69.58,
      "roc12": -14.77
    },
    {
      "month": "2024-11",
      "date": "2024-11-01",
      "open": 69.81,
      "high": 72.69,
      "low": 67.33,
      "close": 68.26,
      "roc12": -9.78
    },
    {
      "month": "2024-12",
      "date": "2024-12-01",
      "open": 68.35,
      "high": 72.44,
      "low": 68.35,
      "close": 72.44,
      "roc12": 0.77
    },
    {
      "month": "2025-01",
      "date": "2025-01-01",
      "open": 73.79,
      "high": 80.73,
      "low": 72.84,
      "close": 72.84,
      "roc12": -4.51
    },
    {
      "month": "2025-02",
      "date": "2025-02-01",
      "open": 73.52,
      "high": 73.67,
      "low": 68.87,
      "close": 69.97,
      "roc12": -11.68
    },
    {
      "month": "2025-03",
      "date": "2025-03-01",
      "open": 68.63,
      "high": 71.87,
      "low": 66.31,
      "close": 71.87,
      "roc12": -14.4
    },
    {
      "month": "2025-04",
      "date": "2025-04-01",
      "open": 71.61,
      "high": 72.12,
      "low": 59.55,
      "close": 59.55,
      "roc12": -28.67
    },
    {
      "month": "2025-05",
      "date": "2025-05-01",
      "open": 60.59,
      "high": 65.04,
      "low": 58.5,
      "close": 61.46,
      "roc12": -21.17
    },
    {
      "month": "2025-06",
      "date": "2025-06-01",
      "open": 63.27,
      "high": 75.89,
      "low": 63.27,
      "close": 66.3,
      "roc12": -19.96
    },
    {
      "month": "2025-07",
      "date": "2025-07-01",
      "open": 66.64,
      "high": 71.09,
      "low": 66.05,
      "close": 70.36,
      "roc12": -11.34
    },
    {
      "month": "2025-08",
      "date": "2025-08-01",
      "open": 68.39,
      "high": 68.39,
      "low": 63.38,
      "close": 64.36,
      "roc12": -13.63
    },
    {
      "month": "2025-09",
      "date": "2025-09-01",
      "open": 65.95,
      "high": 66.5,
      "low": 62.22,
      "close": 63.17,
      "roc12": -8.12
    },
    {
      "month": "2025-10",
      "date": "2025-10-01",
      "open": 62.59,
      "high": 63.37,
      "low": 58.29,
      "close": 61.75,
      "roc12": -11.25
    },
    {
      "month": "2025-11",
      "date": "2025-11-01",
      "open": 61.79,
      "high": 61.79,
      "low": 58.25,
      "close": 58.58,
      "roc12": -14.18
    },
    {
      "month": "2025-12",
      "date": "2025-12-01",
      "open": 59.47,
      "high": 60.23,
      "low": 55.44,
      "close": 57.26,
      "roc12": -20.96
    },
    {
      "month": "2026-01",
      "date": "2026-01-01",
      "open": 57.21,
      "high": 64.77,
      "low": 56.01,
      "close": 64.5,
      "roc12": -11.45
    },
    {
      "month": "2026-02",
      "date": "2026-02-01",
      "open": 61.6,
      "high": 66.96,
      "low": 61.6,
      "close": 66.96,
      "roc12": -4.3
    },
    {
      "month": "2026-03",
      "date": "2026-03-01",
      "open": 71.13,
      "high": 104.69,
      "low": 71.13,
      "close": 104.69,
      "roc12": 45.67
    },
    {
      "month": "2026-04",
      "date": "2026-04-01",
      "open": 101.72,
      "high": 113.97,
      "low": 96.5,
      "close": 111.54,
      "snapshotDate": "2026-04-02",
      "snapshotSource": "StockCharts reference snapshot provided by user",
      "roc12": 87.3
    }
  ]
}